kahi_doaj_sources/Kahi_doaj_sources.py
kahi_doaj_sources/__init__.py
kahi_doaj_sources/_version.py
Kahi_doaj_sources-0.1.1b0.dist-info/LICENSE
Kahi_doaj_sources-0.1.1b0.dist-info/METADATA
Kahi_doaj_sources-0.1.1b0.dist-info/WHEEL
Kahi_doaj_sources-0.1.1b0.dist-info/top_level.txt
Kahi_doaj_sources-0.1.1b0.dist-info/RECORD
