Metadata-Version: 2.1
Name: Kahi_doaj_sources
Version: 0.1.1b0
Summary: Kahi plugin doaj_sources
Home-page: https://github.com/colav/Kahi_plugins
Author: Colav
Author-email: colav@udea.edu.co
License: BSD
License-File: LICENSE
Requires-Dist: kahi
Requires-Dist: pymongo
Requires-Dist: datetime
